setup.py
test/__init__.py
test/test_applicant.py
test/test_base.py
test/test_carrier.py
test/test_carrier_subsidiary.py
test/test_county.py
test/test_county_bulk.py
test/test_drug.py
test/test_drug_coverage.py
test/test_drug_coverage_response.py
test/test_drug_coverages_api.py
test/test_drug_package.py
test/test_drug_packages_api.py
test/test_drug_search_response.py
test/test_drugs_api.py
test/test_formulary.py
test/test_formulary_drug_package_response.py
test/test_formulary_response.py
test/test_meta.py
test/test_network.py
test/test_network_details.py
test/test_network_details_response.py
test/test_network_search_response.py
test/test_network_size.py
test/test_network_sizes_api.py
test/test_networks_api.py
test/test_plan.py
test/test_plan_county.py
test/test_plan_county_bulk.py
test/test_plan_search_response.py
test/test_plan_search_response_meta.py
test/test_plan_search_result.py
test/test_plan_show_response.py
test/test_plans_api.py
test/test_provider.py
test/test_provider_details.py
test/test_provider_geocode.py
test/test_provider_show_response.py
test/test_providers_api.py
test/test_providers_geocode_response.py
test/test_providers_search_response.py
test/test_rating_area.py
test/test_request_plan_find.py
test/test_request_plan_find_applicant.py
test/test_request_plan_find_drug_package.py
test/test_request_plan_find_provider.py
test/test_request_providers_search.py
test/test_service_area.py
test/test_service_area_zip_county.py
test/test_state.py
test/test_state_network_size_request.py
test/test_state_network_size_response.py
test/test_zip_code.py
test/test_zip_counties_api.py
test/test_zip_counties_response.py
test/test_zip_county.py
test/test_zip_county_bulk.py
test/test_zip_county_response.py
vericred_client/__init__.py
vericred_client/api_client.py
vericred_client/configuration.py
vericred_client/rest.py
vericred_client.egg-info/PKG-INFO
vericred_client.egg-info/SOURCES.txt
vericred_client.egg-info/dependency_links.txt
vericred_client.egg-info/requires.txt
vericred_client.egg-info/top_level.txt
vericred_client/apis/__init__.py
vericred_client/apis/drug_coverages_api.py
vericred_client/apis/drug_packages_api.py
vericred_client/apis/drugs_api.py
