Metadata-Version: 1.0
Name: vericred-client
Version: 0.0.9
Summary: Vericred API
Home-page: UNKNOWN
Author: UNKNOWN
Author-email: UNKNOWN
License: UNKNOWN
Keywords: Swagger,Vericred API
Platform: UNKNOWN
